trajectory_processing/__init__.py
trajectory_processing/preprocess.py
trajectory_processing/settings.py
trajectory_processing/utils.py
trajectory_processing-0.4.6.dist-info/METADATA
trajectory_processing-0.4.6.dist-info/WHEEL
trajectory_processing-0.4.6.dist-info/top_level.txt
trajectory_processing-0.4.6.dist-info/RECORD
